<?xml version="1.0" encoding="UTF-8"?>
  <PRPT>
    <OH>
      <row>
        <OH_IDNR>1008527</OH_IDNR>
        <OH_AEVERSION>11.2</OH_AEVERSION>
        <OH_CHILDFLAGS>00000000000000000000000000000000</OH_CHILDFLAGS>
        <OH_CRDATE>2018-06-12 14:25:27.0</OH_CRDATE>
        <OH_CRUSERIDNR>1001003</OH_CRUSERIDNR>
        <OH_LASTRUNS>AAAAAAAAAAAAAAAAAAAAAAAAAAAAAAAA</OH_LASTRUNS>
        <OH_MODUSERIDNR>1001003</OH_MODUSERIDNR>
        <OH_MPELSE>1</OH_MPELSE>
        <OH_MRTTIME>000000</OH_MRTTIME>
        <OH_NAME>PCK.AUTOMIC_TOMCAT.PRV.PROMPTSET.UNDEPLOY_APPLICATION</OH_NAME>
        <OH_OTYPE>PRPT</OH_OTYPE>
        <OH_QUEUE>CLIENT_QUEUE</OH_QUEUE>
        <OH_VERSIONINGID> </OH_VERSIONINGID>
      </row>
    </OH>
    <OPSA>
      <row>
        <OPSA_XUI>&lt;dialog height="506" icon="PRPT" id="PRPTS" left="279" top="4" width="420"&gt;&lt;readpanel fill="b" id="PRPTBOX" nl="1" scroll="v" text="Parameters"&gt;&lt;properties&gt;&lt;entry name="text"&gt;Parameters&lt;/entry&gt;&lt;entry name="modifiable"&gt;0&lt;/entry&gt;&lt;/properties&gt;&lt;/readpanel&gt;&lt;/dialog&gt;</OPSA_XUI>
      </row>
    </OPSA>
    <OPSE>
      <row>
        <OPSE_LNR>6</OPSE_LNR>
        <OPSE_MSGNR>-1</OPSE_MSGNR>
        <OPSE_NAME>UC4RB_TC_APPBASE#</OPSE_NAME>
        <OPSE_REFNAME>UC_DATATYPE_STRING</OPSE_REFNAME>
        <OPSE_REFTYPE>VARA</OPSE_REFTYPE>
        <OPSE_REQUIRED>1</OPSE_REQUIRED>
        <OPSE_SEPARATEDBY>;</OPSE_SEPARATEDBY>
        <OPSE_XUI>&lt;text enabled="1" fill="b" focus="0" id="UC4RB_TC_APPBASEs.00" inputassistance="0" len="" nl="1" regex="" separator=";" showaspassword="0" text="App-base" tooltip="Name of the directory, where the web applications are located. Usually it is found in the directory &amp;apos;webapps&amp;apos; in your Tomcat home." upper="0" required="0" alt="1" multiline="0" multilineIcon="0"&gt;&lt;oninputassistant&gt;&lt;command request="_internal" target="_view" targetaction="setAttribute" targetparam="promptname|@id"/&gt;&lt;command request="_internal" target="_view" targetaction="setAttribute" targetparam="promptvalue|@value"/&gt;&lt;command owner="_promptsetcontainer" owneraction="getData" request="getpromptinputassistance" target="_chainwindow"/&gt;&lt;/oninputassistant&gt;&lt;properties&gt;&lt;entry listparam="C" name="reference" reftype="STATIC"&gt;UC_DATATYPE_STRING&lt;/entry&gt;&lt;entry name="text"&gt;App-base&lt;/entry&gt;&lt;entry name="multiselect"&gt;0&lt;/entry&gt;&lt;entry name="separator"&gt;;&lt;/entry&gt;&lt;entry name="len"/&gt;&lt;entry name="quotes"/&gt;&lt;entry name="id"&gt;UC4RB_TC_APPBASEs.00&lt;/entry&gt;&lt;entry name="inputassistance"&gt;0&lt;/entry&gt;&lt;entry name="enabled"&gt;0&lt;/entry&gt;&lt;entry name="upper"&gt;0&lt;/entry&gt;&lt;entry name="focus"&gt;0&lt;/entry&gt;&lt;entry name="showaspassword"&gt;0&lt;/entry&gt;&lt;entry name="tooltip"&gt;Name of the directory, where the web applications are located. Usually it is found in the directory &amp;apos;webapps&amp;apos; in your Tomcat home.&lt;/entry&gt;&lt;entry name="customfield"/&gt;&lt;entry name="modifiable"&gt;1&lt;/entry&gt;&lt;entry name="regex"/&gt;&lt;entry name="required"&gt;1&lt;/entry&gt;&lt;entry name="initvalue"/&gt;&lt;entry name="xmlkey"/&gt;&lt;entry name="xmlpath"/&gt;&lt;entry name="multiline"&gt;0&lt;/entry&gt;&lt;entry name="multilineIcon"&gt;0&lt;/entry&gt;&lt;entry name="onchangereset"/&gt;&lt;entry name="resetable"&gt;1&lt;/entry&gt;&lt;/properties&gt;&lt;/text&gt;</OPSE_XUI>
        <OPSE_XUI_TYPE>text</OPSE_XUI_TYPE>
      </row>
      <row>
        <OPSE_LNR>2</OPSE_LNR>
        <OPSE_MSGNR>-1</OPSE_MSGNR>
        <OPSE_NAME>UC4RB_TC_BASE_URL#</OPSE_NAME>
        <OPSE_REFNAME>UC_DATATYPE_STRING</OPSE_REFNAME>
        <OPSE_REFTYPE>VARA</OPSE_REFTYPE>
        <OPSE_REQUIRED>1</OPSE_REQUIRED>
        <OPSE_SEPARATEDBY>;</OPSE_SEPARATEDBY>
        <OPSE_XUI>&lt;text enabled="1" fill="b" focus="0" id="UC4RB_TC_BASE_URLs.00" inputassistance="0" len="" nl="1" regex="" separator=";" showaspassword="0" text="Tomcat Base URL" tooltip="URL pointing to your Tomcat installation. E.g.: http://localhost:8080/" upper="0" required="0" alt="1" multiline="0" multilineIcon="0"&gt;&lt;oninputassistant&gt;&lt;command request="_internal" target="_view" targetaction="setAttribute" targetparam="promptname|@id"/&gt;&lt;command request="_internal" target="_view" targetaction="setAttribute" targetparam="promptvalue|@value"/&gt;&lt;command owner="_promptsetcontainer" owneraction="getData" request="getpromptinputassistance" target="_chainwindow"/&gt;&lt;/oninputassistant&gt;&lt;properties&gt;&lt;entry listparam="C" name="reference" reftype="STATIC"&gt;UC_DATATYPE_STRING&lt;/entry&gt;&lt;entry name="text"&gt;Tomcat Base URL&lt;/entry&gt;&lt;entry name="multiselect"&gt;0&lt;/entry&gt;&lt;entry name="separator"&gt;;&lt;/entry&gt;&lt;entry name="len"/&gt;&lt;entry name="quotes"/&gt;&lt;entry name="id"&gt;UC4RB_TC_BASE_URLs.00&lt;/entry&gt;&lt;entry name="inputassistance"&gt;0&lt;/entry&gt;&lt;entry name="enabled"&gt;0&lt;/entry&gt;&lt;entry name="upper"&gt;0&lt;/entry&gt;&lt;entry name="focus"&gt;0&lt;/entry&gt;&lt;entry name="showaspassword"&gt;0&lt;/entry&gt;&lt;entry name="tooltip"&gt;URL pointing to your Tomcat installation. E.g.: http://localhost:8080/&lt;/entry&gt;&lt;entry name="customfield"/&gt;&lt;entry name="modifiable"&gt;1&lt;/entry&gt;&lt;entry name="regex"/&gt;&lt;entry name="required"&gt;1&lt;/entry&gt;&lt;entry name="initvalue"/&gt;&lt;entry name="xmlkey"/&gt;&lt;entry name="xmlpath"/&gt;&lt;entry name="multiline"&gt;0&lt;/entry&gt;&lt;entry name="multilineIcon"&gt;0&lt;/entry&gt;&lt;entry name="onchangereset"/&gt;&lt;entry name="resetable"&gt;1&lt;/entry&gt;&lt;/properties&gt;&lt;/text&gt;</OPSE_XUI>
        <OPSE_XUI_TYPE>text</OPSE_XUI_TYPE>
      </row>
      <row>
        <OPSE_LNR>7</OPSE_LNR>
        <OPSE_MSGNR>-1</OPSE_MSGNR>
        <OPSE_NAME>UC4RB_TC_CONTEXT_PATH#</OPSE_NAME>
        <OPSE_REFNAME>UC_DATATYPE_STRING</OPSE_REFNAME>
        <OPSE_REFTYPE>VARA</OPSE_REFTYPE>
        <OPSE_REQUIRED>1</OPSE_REQUIRED>
        <OPSE_SEPARATEDBY>;</OPSE_SEPARATEDBY>
        <OPSE_XUI>&lt;text enabled="1" fill="b" focus="0" id="UC4RB_TC_CONTEXT_PATHs.00" inputassistance="0" len="" nl="1" regex="" separator=";" showaspassword="0" text="Context path" tooltip="The context path (including the leading slash) of the web application you are dealing with. To select the ROOT web application, specify &amp;quot;/&amp;quot;." upper="0" required="0" alt="1" multiline="0" multilineIcon="0"&gt;&lt;oninputassistant&gt;&lt;command request="_internal" target="_view" targetaction="setAttribute" targetparam="promptname|@id"/&gt;&lt;command request="_internal" target="_view" targetaction="setAttribute" targetparam="promptvalue|@value"/&gt;&lt;command owner="_promptsetcontainer" owneraction="getData" request="getpromptinputassistance" target="_chainwindow"/&gt;&lt;/oninputassistant&gt;&lt;properties&gt;&lt;entry listparam="C" name="reference" reftype="STATIC"&gt;UC_DATATYPE_STRING&lt;/entry&gt;&lt;entry name="text"&gt;Context path&lt;/entry&gt;&lt;entry name="multiselect"&gt;0&lt;/entry&gt;&lt;entry name="separator"&gt;;&lt;/entry&gt;&lt;entry name="len"/&gt;&lt;entry name="quotes"/&gt;&lt;entry name="id"&gt;UC4RB_TC_CONTEXT_PATHs.00&lt;/entry&gt;&lt;entry name="inputassistance"&gt;0&lt;/entry&gt;&lt;entry name="enabled"&gt;0&lt;/entry&gt;&lt;entry name="upper"&gt;0&lt;/entry&gt;&lt;entry name="focus"&gt;0&lt;/entry&gt;&lt;entry name="showaspassword"&gt;0&lt;/entry&gt;&lt;entry name="tooltip"&gt;The context path (including the leading slash) of the web application you are dealing with. To select the ROOT web application, specify &amp;quot;/&amp;quot;.&lt;/entry&gt;&lt;entry name="customfield"/&gt;&lt;entry name="modifiable"&gt;1&lt;/entry&gt;&lt;entry name="regex"/&gt;&lt;entry name="required"&gt;1&lt;/entry&gt;&lt;entry name="initvalue"/&gt;&lt;entry name="xmlkey"/&gt;&lt;entry name="xmlpath"/&gt;&lt;entry name="multiline"&gt;0&lt;/entry&gt;&lt;entry name="multilineIcon"&gt;0&lt;/entry&gt;&lt;entry name="onchangereset"/&gt;&lt;entry name="resetable"&gt;1&lt;/entry&gt;&lt;/properties&gt;&lt;/text&gt;</OPSE_XUI>
        <OPSE_XUI_TYPE>text</OPSE_XUI_TYPE>
      </row>
      <row>
        <OPSE_LNR>8</OPSE_LNR>
        <OPSE_MSGNR>-1</OPSE_MSGNR>
        <OPSE_NAME>UC4RB_TC_FAIL_IF_NOT_DEPLOYED#</OPSE_NAME>
        <OPSE_REFNAME>PCK.ITPA_SHARED.PRV.VARA.YES_NO</OPSE_REFNAME>
        <OPSE_REFTYPE>VARA</OPSE_REFTYPE>
        <OPSE_VALUE>NO</OPSE_VALUE>
        <OPSE_XUI>&lt;dynradiogroup enabled="1" fill="b" focus="0" id="UC4RB_TC_FAIL_IF_NOT_DEPLOYEDs.00" nl="1" quotes="" text="Fail if not deployed" tooltip="The action fails with an error message (err. 1) if the application has not been deployed and you try the undeploy it. " alt="1" required="0"&gt;&lt;properties&gt;&lt;entry listparam="C" name="reference" reftype="STATIC"&gt;PCK.ITPA_SHARED.PRV.VARA.YES_NO&lt;/entry&gt;&lt;entry name="text"&gt;Fail if not deployed&lt;/entry&gt;&lt;entry name="quotes"/&gt;&lt;entry name="id"&gt;UC4RB_TC_FAIL_IF_NOT_DEPLOYEDs.00&lt;/entry&gt;&lt;entry name="enabled"&gt;0&lt;/entry&gt;&lt;entry name="focus"&gt;0&lt;/entry&gt;&lt;entry name="tooltip"&gt;The action fails with an error message (err. 1) if the application has not been deployed and you try the undeploy it. &lt;/entry&gt;&lt;entry name="customfield"/&gt;&lt;entry name="modifiable"&gt;1&lt;/entry&gt;&lt;entry name="initvalue"/&gt;&lt;entry name="xmlkey"/&gt;&lt;entry name="xmlpath"/&gt;&lt;/properties&gt;&lt;/dynradiogroup&gt;</OPSE_XUI>
        <OPSE_XUI_TYPE>dynradiogroup</OPSE_XUI_TYPE>
      </row>
      <row>
        <OPSE_LNR>1</OPSE_LNR>
        <OPSE_MSGNR>-1</OPSE_MSGNR>
        <OPSE_NAME>UC4RB_TC_HOME_DIR#</OPSE_NAME>
        <OPSE_REFNAME>UC_DATATYPE_STRING</OPSE_REFNAME>
        <OPSE_REFTYPE>VARA</OPSE_REFTYPE>
        <OPSE_REQUIRED>1</OPSE_REQUIRED>
        <OPSE_SEPARATEDBY>;</OPSE_SEPARATEDBY>
        <OPSE_XUI>&lt;text enabled="1" fill="b" focus="0" id="UC4RB_TC_HOME_DIRs.00" inputassistance="0" len="" nl="1" regex="" separator=";" showaspassword="0" text="Tomcat home" tooltip="Path to the Tomcat home directory on the executing machine. Eg: C:\Program Files\Apache Software Foundations\Tomcat7\" upper="0" required="0" alt="1" multiline="0" multilineIcon="0"&gt;&lt;oninputassistant&gt;&lt;command request="_internal" target="_view" targetaction="setAttribute" targetparam="promptname|@id"/&gt;&lt;command request="_internal" target="_view" targetaction="setAttribute" targetparam="promptvalue|@value"/&gt;&lt;command owner="_promptsetcontainer" owneraction="getData" request="getpromptinputassistance" target="_chainwindow"/&gt;&lt;/oninputassistant&gt;&lt;properties&gt;&lt;entry listparam="C" name="reference" reftype="STATIC"&gt;UC_DATATYPE_STRING&lt;/entry&gt;&lt;entry name="text"&gt;Tomcat home&lt;/entry&gt;&lt;entry name="multiselect"&gt;0&lt;/entry&gt;&lt;entry name="separator"&gt;;&lt;/entry&gt;&lt;entry name="len"/&gt;&lt;entry name="quotes"/&gt;&lt;entry name="id"&gt;UC4RB_TC_HOME_DIRs.00&lt;/entry&gt;&lt;entry name="inputassistance"&gt;0&lt;/entry&gt;&lt;entry name="enabled"&gt;0&lt;/entry&gt;&lt;entry name="upper"&gt;0&lt;/entry&gt;&lt;entry name="focus"&gt;0&lt;/entry&gt;&lt;entry name="showaspassword"&gt;0&lt;/entry&gt;&lt;entry name="tooltip"&gt;Path to the Tomcat home directory on the executing machine. Eg: C:\Program Files\Apache Software Foundations\Tomcat7\&lt;/entry&gt;&lt;entry name="customfield"/&gt;&lt;entry name="modifiable"&gt;1&lt;/entry&gt;&lt;entry name="regex"/&gt;&lt;entry name="required"&gt;1&lt;/entry&gt;&lt;entry name="initvalue"/&gt;&lt;entry name="xmlkey"/&gt;&lt;entry name="xmlpath"/&gt;&lt;entry name="multiline"&gt;0&lt;/entry&gt;&lt;entry name="multilineIcon"&gt;0&lt;/entry&gt;&lt;entry name="onchangereset"/&gt;&lt;entry name="resetable"&gt;1&lt;/entry&gt;&lt;/properties&gt;&lt;/text&gt;</OPSE_XUI>
        <OPSE_XUI_TYPE>text</OPSE_XUI_TYPE>
      </row>
      <row>
        <OPSE_LNR>3</OPSE_LNR>
        <OPSE_MSGNR>-1</OPSE_MSGNR>
        <OPSE_NAME>UC4RB_TC_MGR_APP#</OPSE_NAME>
        <OPSE_REFNAME>UC_DATATYPE_STRING</OPSE_REFNAME>
        <OPSE_REFTYPE>VARA</OPSE_REFTYPE>
        <OPSE_REQUIRED>1</OPSE_REQUIRED>
        <OPSE_SEPARATEDBY>;</OPSE_SEPARATEDBY>
        <OPSE_VALUE>manager</OPSE_VALUE>
        <OPSE_XUI>&lt;text enabled="1" fill="b" focus="0" id="UC4RB_TC_MGR_APPs.00" inputassistance="0" len="" nl="1" regex="" separator=";" showaspassword="0" text="Manage app" tooltip="Name of the manager application, which is usually called &amp;quot;manager&amp;quot;." upper="0" required="0" alt="1" multiline="0" multilineIcon="0"&gt;&lt;oninputassistant&gt;&lt;command request="_internal" target="_view" targetaction="setAttribute" targetparam="promptname|@id"/&gt;&lt;command request="_internal" target="_view" targetaction="setAttribute" targetparam="promptvalue|@value"/&gt;&lt;command owner="_promptsetcontainer" owneraction="getData" request="getpromptinputassistance" target="_chainwindow"/&gt;&lt;/oninputassistant&gt;&lt;properties&gt;&lt;entry listparam="C" name="reference" reftype="STATIC"&gt;UC_DATATYPE_STRING&lt;/entry&gt;&lt;entry name="text"&gt;Manage app&lt;/entry&gt;&lt;entry name="multiselect"&gt;0&lt;/entry&gt;&lt;entry name="separator"&gt;;&lt;/entry&gt;&lt;entry name="len"/&gt;&lt;entry name="quotes"/&gt;&lt;entry name="id"&gt;UC4RB_TC_MGR_APPs.00&lt;/entry&gt;&lt;entry name="inputassistance"&gt;0&lt;/entry&gt;&lt;entry name="enabled"&gt;0&lt;/entry&gt;&lt;entry name="upper"&gt;0&lt;/entry&gt;&lt;entry name="focus"&gt;0&lt;/entry&gt;&lt;entry name="showaspassword"&gt;0&lt;/entry&gt;&lt;entry name="tooltip"&gt;Name of the manager application, which is usually called &amp;quot;manager&amp;quot;.&lt;/entry&gt;&lt;entry name="customfield"/&gt;&lt;entry name="modifiable"&gt;1&lt;/entry&gt;&lt;entry name="regex"/&gt;&lt;entry name="required"&gt;1&lt;/entry&gt;&lt;entry name="initvalue"/&gt;&lt;entry name="xmlkey"/&gt;&lt;entry name="xmlpath"/&gt;&lt;entry name="multiline"&gt;0&lt;/entry&gt;&lt;entry name="multilineIcon"&gt;0&lt;/entry&gt;&lt;entry name="onchangereset"/&gt;&lt;entry name="resetable"&gt;1&lt;/entry&gt;&lt;/properties&gt;&lt;/text&gt;</OPSE_XUI>
        <OPSE_XUI_TYPE>text</OPSE_XUI_TYPE>
      </row>
      <row>
        <OPSE_LNR>5</OPSE_LNR>
        <OPSE_MSGNR>-1</OPSE_MSGNR>
        <OPSE_NAME>UC4RB_TC_PASSWORD#</OPSE_NAME>
        <OPSE_REFNAME>UC_DATATYPE_STRING</OPSE_REFNAME>
        <OPSE_REFTYPE>VARA</OPSE_REFTYPE>
        <OPSE_REQUIRED>1</OPSE_REQUIRED>
        <OPSE_SEPARATEDBY>;</OPSE_SEPARATEDBY>
        <OPSE_SHOWASPW>1</OPSE_SHOWASPW>
        <OPSE_VALUE>--10</OPSE_VALUE>
        <OPSE_XUI>&lt;text enabled="1" fill="b" focus="0" id="UC4RB_TC_PASSWORDs.00" inputassistance="0" len="" nl="1" regex="" separator=";" showaspassword="1" text="Password" tooltip="Password used to manage Tomcat." upper="0" required="0" alt="1" multiline="0" multilineIcon="0"&gt;&lt;oninputassistant&gt;&lt;command request="_internal" target="_view" targetaction="setAttribute" targetparam="promptname|@id"/&gt;&lt;command request="_internal" target="_view" targetaction="setAttribute" targetparam="promptvalue|@value"/&gt;&lt;command owner="_promptsetcontainer" owneraction="getData" request="getpromptinputassistance" target="_chainwindow"/&gt;&lt;/oninputassistant&gt;&lt;properties&gt;&lt;entry listparam="C" name="reference" reftype="STATIC"&gt;UC_DATATYPE_STRING&lt;/entry&gt;&lt;entry name="text"&gt;Password&lt;/entry&gt;&lt;entry name="multiselect"&gt;0&lt;/entry&gt;&lt;entry name="separator"&gt;;&lt;/entry&gt;&lt;entry name="len"/&gt;&lt;entry name="quotes"/&gt;&lt;entry name="id"&gt;UC4RB_TC_PASSWORDs.00&lt;/entry&gt;&lt;entry name="inputassistance"&gt;0&lt;/entry&gt;&lt;entry name="enabled"&gt;0&lt;/entry&gt;&lt;entry name="upper"&gt;0&lt;/entry&gt;&lt;entry name="focus"&gt;0&lt;/entry&gt;&lt;entry name="showaspassword"&gt;1&lt;/entry&gt;&lt;entry name="tooltip"&gt;Password used to manage Tomcat.&lt;/entry&gt;&lt;entry name="customfield"/&gt;&lt;entry name="modifiable"&gt;1&lt;/entry&gt;&lt;entry name="regex"/&gt;&lt;entry name="required"&gt;1&lt;/entry&gt;&lt;entry name="initvalue"/&gt;&lt;entry name="xmlkey"/&gt;&lt;entry name="xmlpath"/&gt;&lt;entry name="multiline"&gt;0&lt;/entry&gt;&lt;entry name="multilineIcon"&gt;0&lt;/entry&gt;&lt;entry name="onchangereset"/&gt;&lt;entry name="resetable"&gt;1&lt;/entry&gt;&lt;/properties&gt;&lt;/text&gt;</OPSE_XUI>
        <OPSE_XUI_TYPE>text</OPSE_XUI_TYPE>
      </row>
      <row>
        <OPSE_LNR>4</OPSE_LNR>
        <OPSE_MSGNR>-1</OPSE_MSGNR>
        <OPSE_NAME>UC4RB_TC_USERNAME#</OPSE_NAME>
        <OPSE_REFNAME>UC_DATATYPE_STRING</OPSE_REFNAME>
        <OPSE_REFTYPE>VARA</OPSE_REFTYPE>
        <OPSE_REQUIRED>1</OPSE_REQUIRED>
        <OPSE_SEPARATEDBY>;</OPSE_SEPARATEDBY>
        <OPSE_XUI>&lt;text enabled="1" fill="b" focus="0" id="UC4RB_TC_USERNAMEs.00" inputassistance="0" len="" nl="1" regex="" separator=";" showaspassword="0" text="Username" tooltip="Username used to manage Tomcat. The user needs the role &amp;quot;manage-script&amp;quot; role assigned." upper="0" required="0" alt="1" multiline="0" multilineIcon="0"&gt;&lt;oninputassistant&gt;&lt;command request="_internal" target="_view" targetaction="setAttribute" targetparam="promptname|@id"/&gt;&lt;command request="_internal" target="_view" targetaction="setAttribute" targetparam="promptvalue|@value"/&gt;&lt;command owner="_promptsetcontainer" owneraction="getData" request="getpromptinputassistance" target="_chainwindow"/&gt;&lt;/oninputassistant&gt;&lt;properties&gt;&lt;entry listparam="C" name="reference" reftype="STATIC"&gt;UC_DATATYPE_STRING&lt;/entry&gt;&lt;entry name="text"&gt;Username&lt;/entry&gt;&lt;entry name="multiselect"&gt;0&lt;/entry&gt;&lt;entry name="separator"&gt;;&lt;/entry&gt;&lt;entry name="len"/&gt;&lt;entry name="quotes"/&gt;&lt;entry name="id"&gt;UC4RB_TC_USERNAMEs.00&lt;/entry&gt;&lt;entry name="inputassistance"&gt;0&lt;/entry&gt;&lt;entry name="enabled"&gt;0&lt;/entry&gt;&lt;entry name="upper"&gt;0&lt;/entry&gt;&lt;entry name="focus"&gt;0&lt;/entry&gt;&lt;entry name="showaspassword"&gt;0&lt;/entry&gt;&lt;entry name="tooltip"&gt;Username used to manage Tomcat. The user needs the role &amp;quot;manage-script&amp;quot; role assigned.&lt;/entry&gt;&lt;entry name="customfield"/&gt;&lt;entry name="modifiable"&gt;1&lt;/entry&gt;&lt;entry name="regex"/&gt;&lt;entry name="required"&gt;1&lt;/entry&gt;&lt;entry name="initvalue"/&gt;&lt;entry name="xmlkey"/&gt;&lt;entry name="xmlpath"/&gt;&lt;entry name="multiline"&gt;0&lt;/entry&gt;&lt;entry name="multilineIcon"&gt;0&lt;/entry&gt;&lt;entry name="onchangereset"/&gt;&lt;entry name="resetable"&gt;1&lt;/entry&gt;&lt;/properties&gt;&lt;/text&gt;</OPSE_XUI>
        <OPSE_XUI_TYPE>text</OPSE_XUI_TYPE>
      </row>
    </OPSE>
  </PRPT>
